examples/__init__.py
tests/__init__.py
tests/test_client.py
tmai_api/__init__.py
tmai_api/base.py
tmai_api/client.py
tmai_api/endpoints/__init__.py
tmai_api/endpoints/ai_agent.py
tmai_api/endpoints/ai_reports.py
tmai_api/endpoints/daily_ohlcv.py
tmai_api/endpoints/hourly_ohlcv.py
tmai_api/endpoints/investor_grades.py
tmai_api/endpoints/market_metrics.py
tmai_api/endpoints/tokens.py
tmai_api/endpoints/trader_grades.py
tmai_api/endpoints/trader_indices.py
tmai_api/endpoints/trading_signals.py
tmai_api-0.4.0.dist-info/LICENSE
tmai_api-0.4.0.dist-info/METADATA
tmai_api-0.4.0.dist-info/WHEEL
tmai_api-0.4.0.dist-info/top_level.txt
tmai_api-0.4.0.dist-info/RECORD
