Metadata-Version: 2.1
Name: tmai-api
Version: 0.4.0
Summary: Python SDK for Token Metrics AI API
Home-page: https://github.com/token-metrics/tmai-api
Author: TMAI
Author-email: talhacagri@tokenmetrics.com
Project-URL: Bug Tracker, https://github.com/token-metrics/tmai-api/issues
Classifier: Programming Language :: Python :: 3
Classifier: License :: OSI Approved :: MIT License
Classifier: Operating System :: OS Independent
License-File: LICENSE
